{
	"name": "12_derivedcolumn",
	"properties": {
		"type": "MappingDataFlow",
		"typeProperties": {
			"sources": [
				{
					"dataset": {
						"referenceName": "AzureSqlTable4",
						"type": "DatasetReference"
					},
					"name": "source1"
				}
			],
			"sinks": [
				{
					"dataset": {
						"referenceName": "AzureSqlTable5_derivedtable",
						"type": "DatasetReference"
					},
					"name": "sink1"
				}
			],
			"transformations": [
				{
					"name": "selectfields"
				},
				{
					"name": "derivedColumn1"
				}
			],
			"scriptLines": [
				"source(output(",
				"          ProductID as integer,",
				"          Name as string,",
				"          ProductNumber as string,",
				"          Color as string,",
				"          StandardCost as decimal(19,4),",
				"          ListPrice as decimal(19,4),",
				"          Size as string,",
				"          Weight as decimal(8,2),",
				"          ProductCategoryID as integer,",
				"          ProductModelID as integer,",
				"          SellStartDate as timestamp,",
				"          SellEndDate as timestamp,",
				"          DiscontinuedDate as timestamp,",
				"          ThumbNailPhoto as binary,",
				"          ThumbnailPhotoFileName as string,",
				"          rowguid as string,",
				"          ModifiedDate as timestamp",
				"     ),",
				"     allowSchemaDrift: true,",
				"     validateSchema: false,",
				"     isolationLevel: 'READ_UNCOMMITTED',",
				"     format: 'table') ~> source1",
				"source1 select(mapColumn(",
				"          ProductID,",
				"          Name,",
				"          ProductNumber,",
				"          ListPrice",
				"     ),",
				"     skipDuplicateMapInputs: true,",
				"     skipDuplicateMapOutputs: true) ~> selectfields",
				"selectfields derive(Listprice_desc = iif(ListPrice >100, 'List price value greater than 100', 'list price value less than 100')) ~> derivedColumn1",
				"derivedColumn1 sink(allowSchemaDrift: true,",
				"     validateSchema: false,",
				"     deletable:false,",
				"     insertable:true,",
				"     updateable:false,",
				"     upsertable:false,",
				"     format: 'table',",
				"     skipDuplicateMapInputs: true,",
				"     skipDuplicateMapOutputs: true,",
				"     errorHandlingOption: 'stopOnFirstError') ~> sink1"
			]
		}
	}
}